RadGEEToolbox/CollectionStitch.py
RadGEEToolbox/Export.py
RadGEEToolbox/GenericCollection.py
RadGEEToolbox/GetPalette.py
RadGEEToolbox/LandsatCollection.py
RadGEEToolbox/Sentinel1Collection.py
RadGEEToolbox/Sentinel2Collection.py
RadGEEToolbox/VisParams.py
RadGEEToolbox/__init__.py
radgeetoolbox-1.7.4.dist-info/licenses/LICENSE.txt
radgeetoolbox-1.7.4.dist-info/METADATA
radgeetoolbox-1.7.4.dist-info/WHEEL
radgeetoolbox-1.7.4.dist-info/top_level.txt
radgeetoolbox-1.7.4.dist-info/RECORD
