Metadata-Version: 2.4
Name: RadGEEToolbox
Version: 1.7.4
Summary: Streamlined Multispectral & SAR Analysis for Google Earth Engine Python API
Home-page: https://github.com/radwinskis/RadGEEToolbox
Author: Mark Radwin
Author-email: Mark Radwin <markradwin@gmail.com>
License: MIT
Project-URL: Homepage, https://github.com/radwinskis/RadGEEToolbox
Project-URL: Documentation, https://radgeetoolbox.readthedocs.io/en/latest/
Project-URL: Issues, https://github.com/radwinskis/RadGEEToolbox/issues
Classifier: Development Status :: 4 - Beta
Classifier: Intended Audience :: Science/Research
Classifier: License :: OSI Approved :: MIT License
Classifier: Programming Language :: Python :: 3
Classifier: Topic :: Scientific/Engineering :: GIS
Classifier: Topic :: Scientific/Engineering :: Information Analysis
Classifier: Operating System :: OS Independent
Requires-Python: >=3.8
License-File: LICENSE.txt
Requires-Dist: earthengine-api
Requires-Dist: numpy
Requires-Dist: pandas
Dynamic: author
Dynamic: home-page
Dynamic: license-file
Dynamic: requires-python
